lib64_dist.pth
dlg/__init__.py
dlg/dask_emulation.py
dlg/ddap_protocol.py
dlg/drop.py
dlg/drop_loaders.py
dlg/droputils.py
dlg/event.py
dlg/graph_loader.py
dlg/meta.py
dlg/named_port_utils.py
dlg/ngaslite.py
dlg/nm_dim_assigner.py
dlg/prepareUser.py
dlg/process.py
dlg/remote.py
dlg/restserver.py
dlg/rpc.py
dlg/shared_memory.py
dlg/testutils.py
dlg/apps/__init__.py
dlg/apps/app_base.py
dlg/apps/archiving.py
dlg/apps/bash_shell_app.py
dlg/apps/branch.py
dlg/apps/constructs.py
dlg/apps/crc.py
dlg/apps/dlg_app.h
dlg/apps/dlg_app2.h
dlg/apps/dockerapp.py
dlg/apps/dynlib.py
dlg/apps/mpi.py
dlg/apps/pyfunc.py
dlg/apps/scp.py
dlg/apps/simple.py
dlg/apps/simple_functions.py
dlg/apps/socket_listener.py
dlg/apps/subgraph.py
dlg/data/__init__.py
dlg/data/io.py
dlg/data/path_builder.py
dlg/data/drops/__init__.py
dlg/data/drops/container.py
dlg/data/drops/data_base.py
dlg/data/drops/directory.py
dlg/data/drops/file.py
dlg/data/drops/json_drop.py
dlg/data/drops/memory.py
dlg/data/drops/ngas.py
dlg/data/drops/parset_drop.py
dlg/data/drops/rdbms.py
dlg/data/drops/s3_drop.py
dlg/deploy/__init__.py
dlg/deploy/common.py
dlg/deploy/create_dlg_job.py
dlg/deploy/deployment_utils.py
dlg/deploy/dlg_monitor.py
dlg/deploy/dlg_proxy.py
dlg/deploy/helm_client.py
dlg/deploy/logparser.py
dlg/deploy/remote_graph.py
dlg/deploy/remotes.py
dlg/deploy/slurm_client.py
dlg/deploy/start_dlg_cluster.py
dlg/deploy/start_helm_cluster.py
dlg/deploy/configs/__init__.py
dlg/deploy/configs/config_manager.py
dlg/deploy/configs/default.ini
dlg/deploy/configs/default.slurm
dlg/deploy/configs/setonix.ini
dlg/deploy/configs/setonix.slurm
dlg/lifecycle/__init__.py
dlg/lifecycle/dlm.py
dlg/lifecycle/registry.py
dlg/lifecycle/hsm/__init__.py
dlg/lifecycle/hsm/manager.py
dlg/lifecycle/hsm/store.py
dlg/manager/__init__.py
dlg/manager/client.py
dlg/manager/cmdline.py
dlg/manager/composite_manager.py
dlg/manager/drop_manager.py
dlg/manager/manager_data.py
dlg/manager/node_manager.py
dlg/manager/past_sessions.py
daliuge_engine-6.4.0.dist-info/METADATA
daliuge_engine-6.4.0.dist-info/WHEEL
daliuge_engine-6.4.0.dist-info/entry_points.txt
daliuge_engine-6.4.0.dist-info/top_level.txt
daliuge_engine-6.4.0.dist-info/RECORD
